<?xml version="1.0" encoding="utf-8" ?>
<dwsync>
<file name="tech-BG.jpg" server="mall.w150.cndns5.com//wwwroot/" local="131331007866164012" remote="131331165600000000" Dst="0" />
<file name="Shopping-WF.jpg" server="mall.w150.cndns5.com//wwwroot/" local="131331356495120283" remote="131331165600000000" Dst="0" />
<file name="360-black-strip.jpg" server="mall.w150.cndns5.com//wwwroot/" local="131329841524381673" remote="131331165600000000" Dst="0" />
<file name="Shopping-BG.jpg" server="mall.w150.cndns5.com//wwwroot/" local="131331400103815696" remote="131331165600000000" Dst="0" />
<file name="filming-WF.jpg" server="mall.w150.cndns5.com//wwwroot/" local="131331353976599790" remote="131331165600000000" Dst="0" />
<file name="Filming-BG.jpg" server="mall.w150.cndns5.com//wwwroot/" local="131331403881001846" remote="131331165600000000" Dst="0" />
<file name="developer-BG.jpg" server="mall.w150.cndns5.com//wwwroot/" local="131329948852922387" remote="131331165600000000" Dst="0" />
<file name="360-BG.jpg" server="mall.w150.cndns5.com//wwwroot/" local="131329841693290824" remote="131331165600000000" Dst="0" />
<file name="ARVR-WF.jpg" server="mall.w150.cndns5.com//wwwroot/" local="131329842161179500" remote="131331165600000000" Dst="0" />
<file name="ARVR-BG.jpg" server="mall.w150.cndns5.com//wwwroot/" local="131329842322078244" remote="131331165600000000" Dst="0" />
<file name="Shopping-WF.psd" server="mall.w150.cndns5.com//wwwroot/" local="131331349101010878" remote="131331166200000000" Dst="0" />
</dwsync>